kekkai/__init__.py
kekkai/cli.py
kekkai/config.py
kekkai/dojo.py
kekkai/dojo_import.py
kekkai/manifest.py
kekkai/output.py
kekkai/paths.py
kekkai/policy.py
kekkai/runner.py
kekkai/compliance/__init__.py
kekkai/compliance/hipaa.py
kekkai/compliance/mappings.py
kekkai/compliance/owasp.py
kekkai/compliance/owasp_agentic.py
kekkai/compliance/pci_dss.py
kekkai/compliance/soc2.py
kekkai/fix/__init__.py
kekkai/fix/audit.py
kekkai/fix/differ.py
kekkai/fix/engine.py
kekkai/fix/prompts.py
kekkai/github/__init__.py
kekkai/github/commenter.py
kekkai/github/models.py
kekkai/github/sanitizer.py
kekkai/installer/__init__.py
kekkai/installer/errors.py
kekkai/installer/extract.py
kekkai/installer/manager.py
kekkai/installer/manifest.py
kekkai/installer/verify.py
kekkai/report/__init__.py
kekkai/report/compliance_matrix.py
kekkai/report/generator.py
kekkai/report/html.py
kekkai/report/pdf.py
kekkai/scanners/__init__.py
kekkai/scanners/base.py
kekkai/scanners/container.py
kekkai/scanners/falco.py
kekkai/scanners/gitleaks.py
kekkai/scanners/semgrep.py
kekkai/scanners/trivy.py
kekkai/scanners/url_policy.py
kekkai/scanners/zap.py
kekkai/scanners/backends/__init__.py
kekkai/scanners/backends/base.py
kekkai/scanners/backends/docker.py
kekkai/scanners/backends/native.py
kekkai/threatflow/__init__.py
kekkai/threatflow/artifacts.py
kekkai/threatflow/chunking.py
kekkai/threatflow/core.py
kekkai/threatflow/mermaid.py
kekkai/threatflow/model_adapter.py
kekkai/threatflow/prompts.py
kekkai/threatflow/redaction.py
kekkai/threatflow/sanitizer.py
kekkai/triage/__init__.py
kekkai/triage/app.py
kekkai/triage/audit.py
kekkai/triage/ignore.py
kekkai/triage/models.py
kekkai/triage/screens.py
kekkai/triage/widgets.py
kekkai_core/__init__.py
kekkai_core/redaction.py
kekkai_core/ci/__init__.py
kekkai_core/ci/benchmarks.py
kekkai_core/ci/metadata.py
kekkai_core/ci/validators.py
kekkai_core/docker/__init__.py
kekkai_core/docker/metadata.py
kekkai_core/docker/sbom.py
kekkai_core/docker/security.py
kekkai_cli-1.1.0.dist-info/METADATA
kekkai_cli-1.1.0.dist-info/WHEEL
kekkai_cli-1.1.0.dist-info/entry_points.txt
kekkai_cli-1.1.0.dist-info/top_level.txt
kekkai_cli-1.1.0.dist-info/RECORD
