Metadata-Version: 2.4
Name: kekkai-cli
Version: 1.1.0
Summary: Kekkai monorepo (local-first AppSec orchestration + compliance checker)
Requires-Python: >=3.12
Requires-Dist: rich>=13.0.0
Requires-Dist: jsonschema>=4.20.0
Requires-Dist: textual>=0.50.0
Requires-Dist: httpx>=0.24.0
